cavalry/__init__.py
cavalry/db_common.py
cavalry/db_django2.py
cavalry/db_django3.py
cavalry/locals.py
cavalry/middleware.py
cavalry/policy.py
cavalry/poster.py
cavalry/reporter.py
cavalry/stack.py
cavalry/timing.py
django_cavalry-0.5.0.dist-info/METADATA
django_cavalry-0.5.0.dist-info/WHEEL
django_cavalry-0.5.0.dist-info/licenses/LICENSE
django_cavalry-0.5.0.dist-info/RECORD
