Metadata-Version: 2.3
Name: django-cavalry
Version: 0.5.0
Summary: Performance tracer middleware for Django
Project-URL: Homepage, https://github.com/valohai/django-cavalry
Author: Valohai
License-Expression: MIT
License-File: LICENSE
Requires-Python: >=3.8
Requires-Dist: django>=2.0
Provides-Extra: dev
Requires-Dist: pytest-cov; extra == 'dev'
Requires-Dist: pytest-django>=3.7.0; extra == 'dev'
Requires-Dist: pytest>=3.0.0; extra == 'dev'
Requires-Dist: requests-mock; extra == 'dev'
Provides-Extra: poster
Requires-Dist: requests; extra == 'poster'
